{
  "iteration": 0,
  "l1_distance": 0,
  "dataset_stats": {
    "total_articles": 248193,
    "total_edges": 3168510
  },
  "top_results": [
    {"rank": 1, "wiki_id": 12, "score": 4.029122e-06},
    {"rank": 2, "wiki_id": 25, "score": 4.029122e-06},
    {"rank": 3, "wiki_id": 39, "score": 4.029122e-06},
    {"rank": 4, "wiki_id": 290, "score": 4.029122e-06},
    {"rank": 5, "wiki_id": 303, "score": 4.029122e-06},
    {"rank": 6, "wiki_id": 305, "score": 4.029122e-06},
    {"rank": 7, "wiki_id": 307, "score": 4.029122e-06},
    {"rank": 8, "wiki_id": 308, "score": 4.029122e-06},
    {"rank": 9, "wiki_id": 309, "score": 4.029122e-06},
    {"rank": 10, "wiki_id": 316, "score": 4.029122e-06},
    {"rank": 11, "wiki_id": 324, "score": 4.029122e-06},
    {"rank": 12, "wiki_id": 334, "score": 4.029122e-06},
    {"rank": 13, "wiki_id": 336, "score": 4.029122e-06},
    {"rank": 14, "wiki_id": 339, "score": 4.029122e-06},
    {"rank": 15, "wiki_id": 340, "score": 4.029122e-06},
    {"rank": 16, "wiki_id": 344, "score": 4.029122e-06},
    {"rank": 17, "wiki_id": 358, "score": 4.029122e-06},
    {"rank": 18, "wiki_id": 359, "score": 4.029122e-06},
    {"rank": 19, "wiki_id": 369, "score": 4.029122e-06},
    {"rank": 20, "wiki_id": 569, "score": 4.029122e-06},
    {"rank": 21, "wiki_id": 572, "score": 4.029122e-06},
    {"rank": 22, "wiki_id": 573, "score": 4.029122e-06},
    {"rank": 23, "wiki_id": 579, "score": 4.029122e-06},
    {"rank": 24, "wiki_id": 580, "score": 4.029122e-06},
    {"rank": 25, "wiki_id": 586, "score": 4.029122e-06},
    {"rank": 26, "wiki_id": 590, "score": 4.029122e-06},
    {"rank": 27, "wiki_id": 593, "score": 4.029122e-06},
    {"rank": 28, "wiki_id": 594, "score": 4.029122e-06},
    {"rank": 29, "wiki_id": 595, "score": 4.029122e-06},
    {"rank": 30, "wiki_id": 597, "score": 4.029122e-06},
    {"rank": 31, "wiki_id": 599, "score": 4.029122e-06},
    {"rank": 32, "wiki_id": 600, "score": 4.029122e-06},
    {"rank": 33, "wiki_id": 612, "score": 4.029122e-06},
    {"rank": 34, "wiki_id": 615, "score": 4.029122e-06},
    {"rank": 35, "wiki_id": 620, "score": 4.029122e-06},
    {"rank": 36, "wiki_id": 621, "score": 4.029122e-06},
    {"rank": 37, "wiki_id": 624, "score": 4.029122e-06},
    {"rank": 38, "wiki_id": 627, "score": 4.029122e-06},
    {"rank": 39, "wiki_id": 628, "score": 4.029122e-06},
    {"rank": 40, "wiki_id": 630, "score": 4.029122e-06},
    {"rank": 41, "wiki_id": 632, "score": 4.029122e-06},
    {"rank": 42, "wiki_id": 633, "score": 4.029122e-06},
    {"rank": 43, "wiki_id": 634, "score": 4.029122e-06},
    {"rank": 44, "wiki_id": 639, "score": 4.029122e-06},
    {"rank": 45, "wiki_id": 640, "score": 4.029122e-06},
    {"rank": 46, "wiki_id": 642, "score": 4.029122e-06},
    {"rank": 47, "wiki_id": 643, "score": 4.029122e-06},
    {"rank": 48, "wiki_id": 644, "score": 4.029122e-06},
    {"rank": 49, "wiki_id": 649, "score": 4.029122e-06},
    {"rank": 50, "wiki_id": 651, "score": 4.029122e-06},
    {"rank": 51, "wiki_id": 653, "score": 4.029122e-06},
    {"rank": 52, "wiki_id": 654, "score": 4.029122e-06},
    {"rank": 53, "wiki_id": 655, "score": 4.029122e-06},
    {"rank": 54, "wiki_id": 656, "score": 4.029122e-06},
    {"rank": 55, "wiki_id": 657, "score": 4.029122e-06},
    {"rank": 56, "wiki_id": 659, "score": 4.029122e-06},
    {"rank": 57, "wiki_id": 661, "score": 4.029122e-06},
    {"rank": 58, "wiki_id": 662, "score": 4.029122e-06},
    {"rank": 59, "wiki_id": 663, "score": 4.029122e-06},
    {"rank": 60, "wiki_id": 664, "score": 4.029122e-06},
    {"rank": 61, "wiki_id": 665, "score": 4.029122e-06},
    {"rank": 62, "wiki_id": 666, "score": 4.029122e-06},
    {"rank": 63, "wiki_id": 668, "score": 4.029122e-06},
    {"rank": 64, "wiki_id": 670, "score": 4.029122e-06},
    {"rank": 65, "wiki_id": 673, "score": 4.029122e-06},
    {"rank": 66, "wiki_id": 674, "score": 4.029122e-06},
    {"rank": 67, "wiki_id": 675, "score": 4.029122e-06},
    {"rank": 68, "wiki_id": 676, "score": 4.029122e-06},
    {"rank": 69, "wiki_id": 677, "score": 4.029122e-06},
    {"rank": 70, "wiki_id": 678, "score": 4.029122e-06},
    {"rank": 71, "wiki_id": 679, "score": 4.029122e-06},
    {"rank": 72, "wiki_id": 680, "score": 4.029122e-06},
    {"rank": 73, "wiki_id": 681, "score": 4.029122e-06},
    {"rank": 74, "wiki_id": 682, "score": 4.029122e-06},
    {"rank": 75, "wiki_id": 683, "score": 4.029122e-06},
    {"rank": 76, "wiki_id": 689, "score": 4.029122e-06},
    {"rank": 77, "wiki_id": 690, "score": 4.029122e-06},
    {"rank": 78, "wiki_id": 691, "score": 4.029122e-06},
    {"rank": 79, "wiki_id": 696, "score": 4.029122e-06},
    {"rank": 80, "wiki_id": 698, "score": 4.029122e-06},
    {"rank": 81, "wiki_id": 700, "score": 4.029122e-06},
    {"rank": 82, "wiki_id": 701, "score": 4.029122e-06},
    {"rank": 83, "wiki_id": 704, "score": 4.029122e-06},
    {"rank": 84, "wiki_id": 705, "score": 4.029122e-06},
    {"rank": 85, "wiki_id": 706, "score": 4.029122e-06},
    {"rank": 86, "wiki_id": 709, "score": 4.029122e-06},
    {"rank": 87, "wiki_id": 710, "score": 4.029122e-06},
    {"rank": 88, "wiki_id": 711, "score": 4.029122e-06},
    {"rank": 89, "wiki_id": 713, "score": 4.029122e-06},
    {"rank": 90, "wiki_id": 717, "score": 4.029122e-06},
    {"rank": 91, "wiki_id": 728, "score": 4.029122e-06},
    {"rank": 92, "wiki_id": 734, "score": 4.029122e-06},
    {"rank": 93, "wiki_id": 736, "score": 4.029122e-06},
    {"rank": 94, "wiki_id": 737, "score": 4.029122e-06},
    {"rank": 95, "wiki_id": 738, "score": 4.029122e-06},
    {"rank": 96, "wiki_id": 740, "score": 4.029122e-06},
    {"rank": 97, "wiki_id": 746, "score": 4.029122e-06},
    {"rank": 98, "wiki_id": 748, "score": 4.029122e-06},
    {"rank": 99, "wiki_id": 751, "score": 4.029122e-06},
    {"rank": 100, "wiki_id": 752, "score": 4.029122e-06}
  ],
  "bottom_results": [
    {"rank": 248094, "wiki_id": 56613112, "score": 4.029122e-06},
    {"rank": 248095, "wiki_id": 56612815, "score": 4.029122e-06},
    {"rank": 248096, "wiki_id": 56612504, "score": 4.029122e-06},
    {"rank": 248097, "wiki_id": 56612437, "score": 4.029122e-06},
    {"rank": 248098, "wiki_id": 56611947, "score": 4.029122e-06},
    {"rank": 248099, "wiki_id": 56611613, "score": 4.029122e-06},
    {"rank": 248100, "wiki_id": 56611433, "score": 4.029122e-06},
    {"rank": 248101, "wiki_id": 56611414, "score": 4.029122e-06},
    {"rank": 248102, "wiki_id": 56611217, "score": 4.029122e-06},
    {"rank": 248103, "wiki_id": 56611146, "score": 4.029122e-06},
    {"rank": 248104, "wiki_id": 56602653, "score": 4.029122e-06},
    {"rank": 248105, "wiki_id": 56602591, "score": 4.029122e-06},
    {"rank": 248106, "wiki_id": 56602583, "score": 4.029122e-06},
    {"rank": 248107, "wiki_id": 56602418, "score": 4.029122e-06},
    {"rank": 248108, "wiki_id": 56593428, "score": 4.029122e-06},
    {"rank": 248109, "wiki_id": 56593304, "score": 4.029122e-06},
    {"rank": 248110, "wiki_id": 56593031, "score": 4.029122e-06},
    {"rank": 248111, "wiki_id": 56592920, "score": 4.029122e-06},
    {"rank": 248112, "wiki_id": 56571945, "score": 4.029122e-06},
    {"rank": 248113, "wiki_id": 56518588, "score": 4.029122e-06},
    {"rank": 248114, "wiki_id": 56245737, "score": 4.029122e-06},
    {"rank": 248115, "wiki_id": 56242826, "score": 4.029122e-06},
    {"rank": 248116, "wiki_id": 56239830, "score": 4.029122e-06},
    {"rank": 248117, "wiki_id": 56228025, "score": 4.029122e-06},
    {"rank": 248118, "wiki_id": 56227907, "score": 4.029122e-06},
    {"rank": 248119, "wiki_id": 56099892, "score": 4.029122e-06},
    {"rank": 248120, "wiki_id": 55974447, "score": 4.029122e-06},
    {"rank": 248121, "wiki_id": 55930918, "score": 4.029122e-06},
    {"rank": 248122, "wiki_id": 55793042, "score": 4.029122e-06},
    {"rank": 248123, "wiki_id": 55442187, "score": 4.029122e-06},
    {"rank": 248124, "wiki_id": 55145549, "score": 4.029122e-06},
    {"rank": 248125, "wiki_id": 55096307, "score": 4.029122e-06},
    {"rank": 248126, "wiki_id": 54682968, "score": 4.029122e-06},
    {"rank": 248127, "wiki_id": 54547496, "score": 4.029122e-06},
    {"rank": 248128, "wiki_id": 54474911, "score": 4.029122e-06},
    {"rank": 248129, "wiki_id": 54332714, "score": 4.029122e-06},
    {"rank": 248130, "wiki_id": 54280735, "score": 4.029122e-06},
    {"rank": 248131, "wiki_id": 54082290, "score": 4.029122e-06},
    {"rank": 248132, "wiki_id": 53865967, "score": 4.029122e-06},
    {"rank": 248133, "wiki_id": 53761076, "score": 4.029122e-06},
    {"rank": 248134, "wiki_id": 53544823, "score": 4.029122e-06},
    {"rank": 248135, "wiki_id": 53435058, "score": 4.029122e-06},
    {"rank": 248136, "wiki_id": 53333563, "score": 4.029122e-06},
    {"rank": 248137, "wiki_id": 53021034, "score": 4.029122e-06},
    {"rank": 248138, "wiki_id": 53020580, "score": 4.029122e-06},
    {"rank": 248139, "wiki_id": 53011534, "score": 4.029122e-06},
    {"rank": 248140, "wiki_id": 53010673, "score": 4.029122e-06},
    {"rank": 248141, "wiki_id": 52712042, "score": 4.029122e-06},
    {"rank": 248142, "wiki_id": 52711223, "score": 4.029122e-06},
    {"rank": 248143, "wiki_id": 52690106, "score": 4.029122e-06},
    {"rank": 248144, "wiki_id": 52593456, "score": 4.029122e-06},
    {"rank": 248145, "wiki_id": 52592913, "score": 4.029122e-06},
    {"rank": 248146, "wiki_id": 52555125, "score": 4.029122e-06},
    {"rank": 248147, "wiki_id": 52337107, "score": 4.029122e-06},
    {"rank": 248148, "wiki_id": 52224017, "score": 4.029122e-06},
    {"rank": 248149, "wiki_id": 52223092, "score": 4.029122e-06},
    {"rank": 248150, "wiki_id": 52177473, "score": 4.029122e-06},
    {"rank": 248151, "wiki_id": 51992830, "score": 4.029122e-06},
    {"rank": 248152, "wiki_id": 51959217, "score": 4.029122e-06},
    {"rank": 248153, "wiki_id": 51905809, "score": 4.029122e-06},
    {"rank": 248154, "wiki_id": 51634966, "score": 4.029122e-06},
    {"rank": 248155, "wiki_id": 51387589, "score": 4.029122e-06},
    {"rank": 248156, "wiki_id": 51142104, "score": 4.029122e-06},
    {"rank": 248157, "wiki_id": 50825276, "score": 4.029122e-06},
    {"rank": 248158, "wiki_id": 50690264, "score": 4.029122e-06},
    {"rank": 248159, "wiki_id": 50436882, "score": 4.029122e-06},
    {"rank": 248160, "wiki_id": 50276696, "score": 4.029122e-06},
    {"rank": 248161, "wiki_id": 50069638, "score": 4.029122e-06},
    {"rank": 248162, "wiki_id": 50037064, "score": 4.029122e-06},
    {"rank": 248163, "wiki_id": 49446160, "score": 4.029122e-06},
    {"rank": 248164, "wiki_id": 48994227, "score": 4.029122e-06},
    {"rank": 248165, "wiki_id": 48933589, "score": 4.029122e-06},
    {"rank": 248166, "wiki_id": 48861264, "score": 4.029122e-06},
    {"rank": 248167, "wiki_id": 48845430, "score": 4.029122e-06},
    {"rank": 248168, "wiki_id": 48779551, "score": 4.029122e-06},
    {"rank": 248169, "wiki_id": 48758386, "score": 4.029122e-06},
    {"rank": 248170, "wiki_id": 48704155, "score": 4.029122e-06},
    {"rank": 248171, "wiki_id": 48694676, "score": 4.029122e-06},
    {"rank": 248172, "wiki_id": 48622023, "score": 4.029122e-06},
    {"rank": 248173, "wiki_id": 48620220, "score": 4.029122e-06},
    {"rank": 248174, "wiki_id": 48587271, "score": 4.029122e-06},
    {"rank": 248175, "wiki_id": 48565835, "score": 4.029122e-06},
    {"rank": 248176, "wiki_id": 48553717, "score": 4.029122e-06},
    {"rank": 248177, "wiki_id": 48429414, "score": 4.029122e-06},
    {"rank": 248178, "wiki_id": 48429222, "score": 4.029122e-06},
    {"rank": 248179, "wiki_id": 48402304, "score": 4.029122e-06},
    {"rank": 248180, "wiki_id": 48400112, "score": 4.029122e-06},
    {"rank": 248181, "wiki_id": 48371980, "score": 4.029122e-06},
    {"rank": 248182, "wiki_id": 48370461, "score": 4.029122e-06},
    {"rank": 248183, "wiki_id": 48345830, "score": 4.029122e-06},
    {"rank": 248184, "wiki_id": 48345285, "score": 4.029122e-06},
    {"rank": 248185, "wiki_id": 48280120, "score": 4.029122e-06},
    {"rank": 248186, "wiki_id": 48201210, "score": 4.029122e-06},
    {"rank": 248187, "wiki_id": 48166872, "score": 4.029122e-06},
    {"rank": 248188, "wiki_id": 48147949, "score": 4.029122e-06},
    {"rank": 248189, "wiki_id": 48140454, "score": 4.029122e-06},
    {"rank": 248190, "wiki_id": 48000504, "score": 4.029122e-06},
    {"rank": 248191, "wiki_id": 47971391, "score": 4.029122e-06},
    {"rank": 248192, "wiki_id": 47962742, "score": 4.029122e-06},
    {"rank": 248193, "wiki_id": 47962699, "score": 4.029122e-06}
  ]
}
